pyflattener/__init__.py
pyflattener/flattener.py
pyflattener-1.1.0.dist-info/LICENSE
pyflattener-1.1.0.dist-info/METADATA
pyflattener-1.1.0.dist-info/WHEEL
pyflattener-1.1.0.dist-info/top_level.txt
pyflattener-1.1.0.dist-info/RECORD
