Metadata-Version: 2.1
Name: pyflattener
Version: 1.1.0
Summary: Flatten nested python objects.
Home-page: https://github.com/swimlane/pyflattener
Author: Swimlane
Author-email: info@swimlane.com
Project-URL: Bug Tracker, https://github.com/swimlane/pyflattener/issues
Classifier: Programming Language :: Python :: 3
Classifier: License :: OSI Approved :: MIT License
Classifier: Operating System :: OS Independent
Requires-Python: >=3.6
License-File: LICENSE
Requires-Dist: datetime-parser <2
Requires-Dist: pendulum >=2.1.2
Requires-Dist: dict-plus ==0.2.3
